{"width":1024,"height":2048,"name":"longkaohuo","imagePath":"longkaohuo_tex.png","SubTexture":[{"width":949,"y":1,"height":678,"name":"longkaohuo/xuedi_","x":1},{"width":112,"y":858,"height":59,"name":"longkaohuo/zuoshou","x":857},{"width":93,"y":681,"height":175,"name":"longkaohuo/weiba","x":857},{"width":429,"y":681,"height":508,"name":"longkaohuo/shenti","x":1},{"width":231,"y":1191,"height":276,"name":"longkaohuo/tou","x":1},{"width":71,"y":919,"height":84,"name":"longkaohuo/youshou","x":857},{"width":423,"y":681,"height":448,"name":"longkaohuo/huoba","x":432},{"width":224,"y":1131,"height":360,"name":"longkaohuo/huoxia","x":432},{"width":224,"y":1131,"height":360,"name":"longkaohuo/huoshang","x":658}]}